Arguments/ArgumentBase.py
Arguments/CommonArguments.py
Arguments/DependencyArguments.py
Arguments/DiprArguments.py
Arguments/ImportArguments.py
Arguments/InitArguments.py
Arguments/PullArguments.py
Arguments/RcsArguments.py
Arguments/ReposArguments.py
Arguments/SourcesArguments.py
Arguments/StatusArguments.py
Arguments/SubReposArguments.py
Arguments/UpdateArguments.py
Arguments/VersionArguments.py
Arguments/__init__.py
Commands/DependsCommand.py
Commands/DiprCommandBase.py
Commands/ImportCommand.py
Commands/InitCommand.py
Commands/PullCommand.py
Commands/RcsCommand.py
Commands/RepoCommandBase.py
Commands/SourcesCommand.py
Commands/StatusCommand.py
Commands/SubReposCommand.py
Commands/UpdateCommand.py
Commands/VersionCommand.py
Commands/__init__.py
Commands/command_line.py
Errors/DiprError.py
Errors/SettingsError.py
Errors/__init__.py
Protocols/AbstractRepoHandler.py
Protocols/ProtocolHelper.py
Protocols/__init__.py
Protocols/Git/GitCommander.py
Protocols/Git/GitRepoHandler.py
Protocols/Git/GitSubmoduleImporter.py
Protocols/Git/__init__.py
Protocols/Hg/HgCommander.py
Protocols/Hg/HgGuestRepoImporter.py
Protocols/Hg/HgRepoHandler.py
Protocols/Hg/__init__.py
Protocols/Hg/hglib/__init__.py
Protocols/Hg/hglib/client.py
Protocols/Hg/hglib/context.py
Protocols/Hg/hglib/error.py
Protocols/Hg/hglib/merge.py
Protocols/Hg/hglib/templates.py
Protocols/Hg/hglib/util.py
Repos/DiprDependencies.py
Repos/DiprRepo.py
Repos/DiprRepoStatus.py
Repos/DiprRepos.py
Repos/DiprResolvedRepo.py
Repos/DiprSource.py
Repos/DiprSources.py
Repos/DiprSubRepos.py
Repos/YamlDict.py
Repos/YamlFile.py
Repos/__init__.py
Settings/GlobalSettings.py
Settings/RepoSettings.py
Settings/UserSettings.py
Settings/__init__.py
Templates/__init__.py
Templates/diprdep.yaml
Templates/diprsrc.yaml
Templates/diprsub.yaml
Utilities/Console.py
Utilities/FileUtilities.py
Utilities/Version.py
Utilities/__init__.py
dipr-1.0.dev12.dist-info/LICENSE.md
dipr-1.0.dev12.dist-info/METADATA
dipr-1.0.dev12.dist-info/WHEEL
dipr-1.0.dev12.dist-info/entry_points.txt
dipr-1.0.dev12.dist-info/top_level.txt
dipr-1.0.dev12.dist-info/RECORD
