Metadata-Version: 2.1
Name: dipr
Version: 1.0.dev12
Summary: A revision control independent dependency and sub-repository management package.
Home-page: http://www.dipr.dev
Author: ZaXa Software, LLC
Author-email: info@zaxasoft.com
License: MIT
Platform: UNKNOWN
Requires-Dist: ruamel.yaml
Requires-Dist: GitPython
Requires-Dist: python-gitlab
